vizibridge-0.6.0.dist-info/METADATA
vizibridge-0.6.0.dist-info/WHEEL
vizibridge-0.6.0.dist-info/licenses/LICENSE
vizibridge/DNA.py
vizibridge/__init__.py
vizibridge/_vizibridge.cpython-39-aarch64-linux-gnu.so
vizibridge/kmer_index.py
vizibridge/kmer_set.py
vizibridge/kmers.py
vizibridge-0.6.0.dist-info/RECORD
