Metadata-Version: 2.4
Name: vizibridge
Version: 0.6.0
Classifier: Programming Language :: Rust
Classifier: Programming Language :: Python :: Implementation :: CPython
Classifier: Programming Language :: Python :: Implementation :: PyPy
Requires-Dist: typing-extensions
License-File: LICENSE
Requires-Python: >=3.8
